CHANGES.txt
README.txt
setup.py
Products/__init__.py
Products.UnicodeLexicon.egg-info/PKG-INFO
Products.UnicodeLexicon.egg-info/SOURCES.txt
Products.UnicodeLexicon.egg-info/dependency_links.txt
Products.UnicodeLexicon.egg-info/namespace_packages.txt
Products.UnicodeLexicon.egg-info/not-zip-safe
Products.UnicodeLexicon.egg-info/requires.txt
Products.UnicodeLexicon.egg-info/top_level.txt
Products/UnicodeLexicon/__init__.py
Products/UnicodeLexicon/accentdata.py
Products/UnicodeLexicon/configure.zcml
Products/UnicodeLexicon/exportimport.py
Products/UnicodeLexicon/interfaces.py
Products/UnicodeLexicon/lexicon.py
Products/UnicodeLexicon/meta.zcml
Products/UnicodeLexicon/metaconfigure.py
Products/UnicodeLexicon/pipeline.py
Products/UnicodeLexicon/pipelinefactory.py
Products/UnicodeLexicon/setuphandlers.py
Products/UnicodeLexicon/version.txt
Products/UnicodeLexicon/profiles/default/catalog.xml
Products/UnicodeLexicon/profiles/default/metadata.xml
Products/UnicodeLexicon/profiles/default/unicodelexicon.txt
Products/UnicodeLexicon/profiles/plone/catalog.xml
Products/UnicodeLexicon/profiles/plone/metadata.xml
Products/UnicodeLexicon/profiles/plone/unicodelexicon.txt
Products/UnicodeLexicon/tests/UnicodeLexiconTestCase.py
Products/UnicodeLexicon/tests/__init__.py
Products/UnicodeLexicon/tests/testDefaultEncoding.py
Products/UnicodeLexicon/tests/testExportImport.py
Products/UnicodeLexicon/tests/testFactory.py
Products/UnicodeLexicon/tests/testLexicon.py
Products/UnicodeLexicon/tests/testSearch.py
Products/UnicodeLexicon/tests/testSetup.py
Products/UnicodeLexicon/tests/testSkeleton.py
Products/UnicodeLexicon/www/addLexicon.dtml
Products/UnicodeLexicon/www/lexicon.gif