Metadata-Version: 1.0
Name: Products.UnicodeLexicon
Version: 2.2
Summary: Unicode aware lexicon for ZCTextIndex
Home-page: http://pypi.python.org/pypi/Products.UnicodeLexicon
Author: Stefan H. Holek
Author-email: stefan@epy.co.at
License: BSD
Keywords: unicode zctextindex
Platform: UNKNOWN
Classifier: Development Status :: 5 - Production/Stable
Classifier: Framework :: Zope2
Classifier: License :: OSI Approved :: BSD License
Classifier: Operating System :: OS Independent
Classifier: Programming Language :: Python :: 2
